setup.cfg
setup.py
tempy/__init__.py
tempy/app.py
tempy.egg-info/PKG-INFO
tempy.egg-info/SOURCES.txt
tempy.egg-info/dependency_links.txt
tempy.egg-info/entry_points.txt
tempy.egg-info/requires.txt
tempy.egg-info/top_level.txt
tempy/scripts/__init__.py
tempy/scripts/analyzer.py
tempy/scripts/cleaner.py
tempy/scripts/config.py
tempy/scripts/converter.py
tempy/scripts/filemanager.py
tests/__init__.py
tests/boilerplate.py
tests/test_tempy.py