Metadata-Version: 1.1
Name: tempy
Version: 0.7
Summary: CLI for cleaning Windows temporary files
Home-page: https://github.com/Dascr32/tempy
Author: Daniel Aguilar S
Author-email: dasgaskl@gmail.com
License: MIT
Download-URL: https://github.com/Dascr32/tempy/archive/v0.7.tar.gz
Keywords: cli temp windows clean delete
Platform: UNKNOWN
Classifier: Development Status :: 4 - Beta
Classifier: Intended Audience :: End Users/Desktop
Classifier: Topic :: Utilities
Classifier: License :: OSI Approved :: MIT License
Classifier: Programming Language :: Python :: 3.4
